odoo/addons/partner_utm_source/README.rst
odoo/addons/partner_utm_source/__init__.py
odoo/addons/partner_utm_source/__manifest__.py
odoo/addons/partner_utm_source/i18n/it.po
odoo/addons/partner_utm_source/i18n/partner_utm_source.pot
odoo/addons/partner_utm_source/models/__init__.py
odoo/addons/partner_utm_source/models/res_partner.py
odoo/addons/partner_utm_source/readme/CONTRIBUTORS.md
odoo/addons/partner_utm_source/readme/DESCRIPTION.md
odoo/addons/partner_utm_source/static/description/icon.png
odoo/addons/partner_utm_source/static/description/index.html
odoo/addons/partner_utm_source/views/partner_views.xml
odoo_addon_partner_utm_source-17.0.1.0.0.4.dist-info/METADATA
odoo_addon_partner_utm_source-17.0.1.0.0.4.dist-info/WHEEL
odoo_addon_partner_utm_source-17.0.1.0.0.4.dist-info/top_level.txt
odoo_addon_partner_utm_source-17.0.1.0.0.4.dist-info/RECORD
