Metadata-Version: 2.1
Name: odoo-addon-partner_utm_source
Version: 17.0.1.0.0.4
Requires-Python: >=3.10
Requires-Dist: odoo>=17.0a,<17.1dev
Summary: This module adds the use of utm source in partners
Home-page: https://github.com/OCA/partner-contact
License: AGPL-3
Author: Trobz, Odoo Community Association (OCA)
Author-email: support@odoo-community.org
Classifier: Programming Language :: Python
Classifier: Framework :: Odoo
Classifier: Framework :: Odoo :: 17.0
Classifier: License :: OSI Approved :: GNU Affero General Public License v3
